{
  "project_info": {
    "project_number": "1090724911560",
    "project_id": "zruriapp",
    "storage_bucket": "zruriapp.appspot.com"
  },
  "client": [
    {
      "client_info": {
        "mobilesdk_app_id": "1:1090724911560:android:22695a5b32432b6d6548fd",
        "android_client_info": {
          "package_name": "com.example.zruri_flutter"
        }
      },
      "oauth_client": [
        {
          "client_id": "1090724911560-gf5k73bhv94fie2f5bv2mt8hchpk1p1e.apps.googleusercontent.com",
          "client_type": 1,
          "android_info": {
            "package_name": "com.example.zruri_flutter",
            "certificate_hash": "c97d12111ac2c3d4faff1f7cd22c9c72bde0c9e5"
          }
        },
        {
          "client_id": "1090724911560-me1q2ei7o7v82g9codb7ei6462ti771l.apps.googleusercontent.com",
          "client_type": 3
        }
      ],
      "api_key": [
        {
          "current_key": "AIzaSyDfG7U1gH4elCi-ZwErA1k3OS-bQ0qViKU"
        }
      ],
      "services": {
        "appinvite_service": {
          "other_platform_oauth_client": [
            {
              "client_id": "1090724911560-me1q2ei7o7v82g9codb7ei6462ti771l.apps.googleusercontent.com",
              "client_type": 3
            },
            {
              "client_id": "1090724911560-7m6n7u4k9o3oqf7klj88u23cdaa80hcl.apps.googleusercontent.com",
              "client_type": 2,
              "ios_info": {
                "bundle_id": "com.example.zruriFlutter"
              }
            }
          ]
        }
      }
    }
  ],
  "configuration_version": "1"
}